jsoncomment/__init__.py
jsoncomment/comments.py
jsoncomment/wrapper.py
jsoncomment-0.4.2.dist-info/COPYING
jsoncomment-0.4.2.dist-info/METADATA
jsoncomment-0.4.2.dist-info/WHEEL
jsoncomment-0.4.2.dist-info/top_level.txt
jsoncomment-0.4.2.dist-info/RECORD
