Metadata-Version: 2.1
Name: jsoncomment
Version: 0.4.2
Summary: A wrapper to JSON parsers allowing comments, multiline strings and trailing commas
Home-page: https://bitbucket.org/Dando_Real_ITA/json-comment
Author: Gaspare Iengo
Author-email: gaspareiengo@gmail.com
License: MIT
Keywords: json comments multiline
Platform: UNKNOWN
Classifier: Development Status :: 4 - Beta
Classifier: Intended Audience :: End Users/Desktop
Classifier: License :: OSI Approved :: MIT License
Classifier: Natural Language :: English
Classifier: Operating System :: OS Independent
Classifier: Programming Language :: Python
Classifier: Programming Language :: Python :: 3.3
Classifier: Topic :: Software Development :: Pre-processors
Classifier: Topic :: Text Editors :: Text Processing
Requires-Python: >=3.3
Provides-Extra: ujson
